{"Alabama":{"display":"Alabama","perCapita":"24091","propertyTax":346277000},"Alaska":{"display":"Alaska","perCapita":"33413","propertyTax":111736000},"Arizona":{"display":"Arizona","perCapita":"25848","propertyTax":943008000},"Arkansas":{"display":"Arkansas","perCapita":"22798","propertyTax":1119958000},"California":{"display":"California","perCapita":"30318","propertyTax":2513157000},"Colorado":{"display":"Colorado","perCapita":"32217","propertyTax":0},"Connecticut":{"display":"Connecticut","perCapita":"38803","propertyTax":0},"Delaware":{"display":"Delaware","perCapita":"30554","propertyTax":0},"District of Columbia":{"display":"District of Columbia","perCapita":"47675","propertyTax":2416604000},"Florida":{"display":"Florida","perCapita":"26829","propertyTax":20000},"Georgia":{"display":"Georgia","perCapita":"25737","propertyTax":961780000},"Hawaii":{"display":"Hawaii","perCapita":"29822","propertyTax":0},"Idaho":{"display":"Idaho","perCapita":"23399","propertyTax":0},"Illinois":{"display":"Illinois","perCapita":"30494","propertyTax":60814000},"Indiana":{"display":"Indiana","perCapita":"25346","propertyTax":10699000},"Iowa":{"display":"Iowa","perCapita":"27950","propertyTax":1410000},"Kansas":{"display":"Kansas","perCapita":"27706","propertyTax":663841000},"Kentucky":{"display":"Kentucky","perCapita":"24063","propertyTax":577544000},"Louisiana":{"display":"Louisiana","perCapita":"24981","propertyTax":62273000},"Maine":{"display":"Maine","perCapita":"27655","propertyTax":35425000},"Maryland":{"display":"Maryland","perCapita":"36897","propertyTax":748389000},"Massachusetts":{"display":"Massachusetts","perCapita":"36895","propertyTax":5818000},"Michigan":{"display":"Michigan","perCapita":"26607","propertyTax":2034013000},"Minnesota":{"display":"Minnesota","perCapita":"32157","propertyTax":849824000},"Mississippi":{"display":"Mississippi","perCapita":"21057","propertyTax":26725000},"Missouri":{"display":"Missouri","perCapita":"26259","propertyTax":30892000},"Montana":{"display":"Montana","perCapita":"26381","propertyTax":278497000},"Nebraska":{"display":"Nebraska","perCapita":"27882","propertyTax":123000},"Nevada":{"display":"Nevada","perCapita":"26541","propertyTax":280055000},"New Hampshire":{"display":"New Hampshire","perCapita":"34362","propertyTax":406394000},"New Jersey":{"display":"New Jersey","perCapita":"36582","propertyTax":4638000},"New Mexico":{"display":"New Mexico","perCapita":"24012","propertyTax":106524000},"New York":{"display":"New York","perCapita":"33236","propertyTax":0},"North Carolina":{"display":"North Carolina","perCapita":"25920","propertyTax":0},"North Dakota":{"display":"North Dakota","perCapita":"32035","propertyTax":3910000},"Ohio":{"display":"Ohio","perCapita":"26953","propertyTax":0},"Oklahoma":{"display":"Oklahoma","perCapita":"25032","propertyTax":0},"Oregon":{"display":"Oregon","perCapita":"27684","propertyTax":20587000},"Pennsylvania":{"display":"Pennsylvania","perCapita":"29291","propertyTax":43124000},"Rhode Island":{"display":"Rhode Island","perCapita":"31118","propertyTax":2544000},"South Carolina":{"display":"South Carolina","perCapita":"24604","propertyTax":32670000},"South Dakota":{"display":"South Dakota","perCapita":"26747","propertyTax":0},"Tennessee":{"display":"Tennessee","perCapita":"25227","propertyTax":0},"Texas":{"display":"Texas","perCapita":"26999","propertyTax":0},"Utah":{"display":"Utah","perCapita":"24686","propertyTax":0},"Vermont":{"display":"Vermont","perCapita":"29894","propertyTax":1056323000},"Virginia":{"display":"Virginia","perCapita":"34152","propertyTax":30367000},"Washington":{"display":"Washington","perCapita":"31762","propertyTax":2062065000},"West Virginia":{"display":"West Virginia","perCapita":"23450","propertyTax":6957000},"Wisconsin":{"display":"Wisconsin","perCapita":"28340","propertyTax":170537000},"Wyoming":{"display":"Wyoming","perCapita":"29803","propertyTax":338776000},"Puerto Rico":{"display":"Puerto Rico","perCapita":"11394"}}